.DS_Store
notipy_me/__init__.py
notipy_me/__version__.py
notipy_me/notipy_me.py
notipy_me-1.0.1.dist-info/LICENSE
notipy_me-1.0.1.dist-info/METADATA
notipy_me-1.0.1.dist-info/WHEEL
notipy_me-1.0.1.dist-info/top_level.txt
notipy_me-1.0.1.dist-info/RECORD
