Metadata-Version: 2.1
Name: notipy-me
Version: 1.0.1
Summary: Test to see if 1D convolutional networks can learn active patterns in genome cellular strains.
Home-page: https://github.com/LucaCappelletti94/notipy_me
Author: Luca Cappelletti
Author-email: cappelletti.luca94@gmail.com
License: MIT
Platform: UNKNOWN
Classifier: Development Status :: 4 - Beta
Classifier: Intended Audience :: Information Technology
Classifier: Topic :: Scientific/Engineering :: Information Analysis
Classifier: License :: OSI Approved :: MIT License
Classifier: Programming Language :: Python :: 3
